seenu_agent/Agent.py
seenu_agent/Task.py
seenu_agent/Task_manager.py
seenu_agent/__init__.py
seenu_agent-0.4.1.dist-info/METADATA
seenu_agent-0.4.1.dist-info/WHEEL
seenu_agent-0.4.1.dist-info/top_level.txt
seenu_agent-0.4.1.dist-info/RECORD
