Metadata-Version: 2.1
Name: seenu-agent
Version: 0.4.1
Summary: A Python package for creating and managing agents.
Author: Seenuvasan T
Author-email: seenuthiruvpm@gmail.com
